{"name":"Travellers with \u003cStatus\u003e level should earn \u003cBonus\u003e bonus points","id":"earning-points;travellers-with-\u003cstatus\u003e-level-should-earn-\u003cbonus\u003e-bonus-points","testSteps":[{"number":1,"description":"1: Travellers with STANDARD level should earn 0 bonus points ({Status\u003dSTANDARD, Points Earned\u003d100, Bonus\u003d0})","duration":14766,"startTime":"2021-05-10T08:17:36.076454167Z[Etc/UTC]","screenshots":[{"screenshot":"f48482bf6147f6b1bdcde8e05ba6e66d92a0043bbed9c2fec3f4813a67c769da.png","timeStamp":1620634670842}],"result":"SUCCESS","precondition":false,"level":0,"lineNumber":93,"children":[{"number":2,"description":"Given Trevor is a Frequent Flyer Member with status STANDARD","duration":230,"startTime":"2021-05-10T08:17:36.077614474Z[Etc/UTC]","result":"SUCCESS","precondition":false,"level":1},{"number":3,"description":"And he has logged onto the Frequent Flyer application","duration":4217,"startTime":"2021-05-10T08:17:36.308608335Z[Etc/UTC]","screenshots":[{"screenshot":"f9b89376250a65427e20386a5efeedca7a520e17ce4e3925e3eea92daf04aff9.png","timeStamp":1620634660525}],"result":"SUCCESS","precondition":false,"level":1,"children":[{"number":4,"description":"he logs in as trevor1386213550@traveller.com","duration":3651,"startTime":"2021-05-10T08:17:36.311643553Z[Etc/UTC]","screenshots":[{"screenshot":"d0f5cd483db5c045b873be3a9315d8a56f0297021bbba522261d7126a320b001.png","timeStamp":1620634659962}],"result":"SUCCESS","precondition":false,"level":2,"children":[{"number":5,"description":"he goes to the login page","duration":3075,"startTime":"2021-05-10T08:17:36.312184856Z[Etc/UTC]","screenshots":[{"screenshot":"5a40d5687e824d8b3dc07abeb1bcf3e2ee3aa4be0c47554157c57950d4204987.png","timeStamp":1620634659388}],"result":"SUCCESS","precondition":false,"level":3,"children":[{"number":6,"description":"he opens the pages.home page","duration":2632,"startTime":"2021-05-10T08:17:36.312826960Z[Etc/UTC]","screenshots":[{"screenshot":"5e6c6fe116f7dbc6222e6991efb3ce925f993a23cc6cc0738806158c1bdaad47.png","timeStamp":1620634658945}],"result":"SUCCESS","precondition":false,"level":4},{"number":7,"description":"he clicks on Login button","duration":436,"startTime":"2021-05-10T08:17:38.946170576Z[Etc/UTC]","screenshots":[{"screenshot":"5e6c6fe116f7dbc6222e6991efb3ce925f993a23cc6cc0738806158c1bdaad47.png","timeStamp":1620634658949},{"screenshot":"5a40d5687e824d8b3dc07abeb1bcf3e2ee3aa4be0c47554157c57950d4204987.png","timeStamp":1620634659382}],"result":"SUCCESS","precondition":false,"level":4}]},{"number":8,"description":"he enters \u0027trevor1386213550@traveller.com\u0027 into Email field","duration":177,"startTime":"2021-05-10T08:17:39.388576382Z[Etc/UTC]","screenshots":[{"screenshot":"5a40d5687e824d8b3dc07abeb1bcf3e2ee3aa4be0c47554157c57950d4204987.png","timeStamp":1620634659391},{"screenshot":"f088bdf27540b73939c3a1e61a970964caf37dc7ece85a954c9e755c3556295c.png","timeStamp":1620634659565}],"result":"SUCCESS","precondition":false,"level":3},{"number":9,"description":"he enters \u0027tr3vor\u0027 into Password field","duration":29,"startTime":"2021-05-10T08:17:39.566462230Z[Etc/UTC]","screenshots":[{"screenshot":"f088bdf27540b73939c3a1e61a970964caf37dc7ece85a954c9e755c3556295c.png","timeStamp":1620634659569},{"screenshot":"f088bdf27540b73939c3a1e61a970964caf37dc7ece85a954c9e755c3556295c.png","timeStamp":1620634659595}],"result":"SUCCESS","precondition":false,"level":3},{"number":10,"description":"he clicks on Login button","duration":364,"startTime":"2021-05-10T08:17:39.596038605Z[Etc/UTC]","screenshots":[{"screenshot":"f088bdf27540b73939c3a1e61a970964caf37dc7ece85a954c9e755c3556295c.png","timeStamp":1620634659598},{"screenshot":"d0f5cd483db5c045b873be3a9315d8a56f0297021bbba522261d7126a320b001.png","timeStamp":1620634659960}],"result":"SUCCESS","precondition":false,"level":3}]},{"number":11,"description":"he expects to see a message of \u0027Logged in as trevor1386213550@traveller.com\u0027","duration":560,"startTime":"2021-05-10T08:17:39.963490870Z[Etc/UTC]","screenshots":[{"screenshot":"d0f5cd483db5c045b873be3a9315d8a56f0297021bbba522261d7126a320b001.png","timeStamp":1620634659964},{"screenshot":"f9b89376250a65427e20386a5efeedca7a520e17ce4e3925e3eea92daf04aff9.png","timeStamp":1620634660524}],"result":"SUCCESS","precondition":false,"level":2,"children":[{"number":12,"description":"he should see Success message with text content that is equal to: \u003c\"Logged in as trevor1386213550@traveller.com\"\u003e","duration":139,"startTime":"2021-05-10T08:17:40.024798431Z[Etc/UTC]","screenshots":[{"screenshot":"37bc56aecf6dacd610d5bbd8a34e68469dfea59eb5f7ea0195c11c8ffb74375a.png","timeStamp":1620634660137},{"screenshot":"37bc56aecf6dacd610d5bbd8a34e68469dfea59eb5f7ea0195c11c8ffb74375a.png","timeStamp":1620634660164}],"result":"SUCCESS","precondition":false,"level":3},{"number":13,"description":"he clicks on Success message","duration":357,"startTime":"2021-05-10T08:17:40.164655755Z[Etc/UTC]","screenshots":[{"screenshot":"37bc56aecf6dacd610d5bbd8a34e68469dfea59eb5f7ea0195c11c8ffb74375a.png","timeStamp":1620634660166},{"screenshot":"f9b89376250a65427e20386a5efeedca7a520e17ce4e3925e3eea92daf04aff9.png","timeStamp":1620634660522}],"result":"SUCCESS","precondition":false,"level":3}]}]},{"number":14,"description":"When he books an Economy flight from Sydney to Hong Kong","duration":9534,"startTime":"2021-05-10T08:17:40.526304186Z[Etc/UTC]","screenshots":[{"screenshot":"f9b89376250a65427e20386a5efeedca7a520e17ce4e3925e3eea92daf04aff9.png","timeStamp":1620634660527},{"screenshot":"441bc43a482312e1592cd31058b9b9b70421ad2a697a07aee0613087ff8ebc05.png","timeStamp":1620634670060}],"result":"SUCCESS","precondition":false,"level":1,"children":[{"number":15,"description":"He search flights","duration":6313,"startTime":"2021-05-10T08:17:40.530277709Z[Etc/UTC]","screenshots":[{"screenshot":"f9b89376250a65427e20386a5efeedca7a520e17ce4e3925e3eea92daf04aff9.png","timeStamp":1620634660531},{"screenshot":"c649aeeb61e4343443f4388d4aad62a04cda4b2095d314b4c520a6278cadcda1.png","timeStamp":1620634666844}],"result":"SUCCESS","precondition":false,"level":2,"children":[{"number":16,"description":"he goes to the Book FLights page","duration":998,"startTime":"2021-05-10T08:17:40.535255139Z[Etc/UTC]","screenshots":[{"screenshot":"f9b89376250a65427e20386a5efeedca7a520e17ce4e3925e3eea92daf04aff9.png","timeStamp":1620634660537},{"screenshot":"31bc1128e80df07850c1a7c72b841e1450f044a5a094b2ec48e0a6bc2ad68fd3.png","timeStamp":1620634661533}],"result":"SUCCESS","precondition":false,"level":3,"children":[{"number":17,"description":"he opens the pages.home page","duration":457,"startTime":"2021-05-10T08:17:40.538350657Z[Etc/UTC]","screenshots":[{"screenshot":"f9b89376250a65427e20386a5efeedca7a520e17ce4e3925e3eea92daf04aff9.png","timeStamp":1620634660541},{"screenshot":"05fd0f2ed615fa3b29070d23f3dc276fdeba6285b27c377e3b7b6e586676dd43.png","timeStamp":1620634660995}],"result":"SUCCESS","precondition":false,"level":4},{"number":18,"description":"he clicks on Book Flights button","duration":533,"startTime":"2021-05-10T08:17:40.996596557Z[Etc/UTC]","screenshots":[{"screenshot":"05fd0f2ed615fa3b29070d23f3dc276fdeba6285b27c377e3b7b6e586676dd43.png","timeStamp":1620634661000},{"screenshot":"31bc1128e80df07850c1a7c72b841e1450f044a5a094b2ec48e0a6bc2ad68fd3.png","timeStamp":1620634661530}],"result":"SUCCESS","precondition":false,"level":4}]},{"number":19,"description":"he enters \u0027Sydney\u0027,TAB into From field","duration":212,"startTime":"2021-05-10T08:17:41.534031723Z[Etc/UTC]","screenshots":[{"screenshot":"31bc1128e80df07850c1a7c72b841e1450f044a5a094b2ec48e0a6bc2ad68fd3.png","timeStamp":1620634661537},{"screenshot":"bd9015237c724da3061c2f94ccfa52add8eca972ab94eb6fe77732b430933188.png","timeStamp":1620634661746}],"result":"SUCCESS","precondition":false,"level":3},{"number":20,"description":"he enters \u0027Hong Kong\u0027,TAB into To field","duration":223,"startTime":"2021-05-10T08:17:41.746902078Z[Etc/UTC]","screenshots":[{"screenshot":"bd9015237c724da3061c2f94ccfa52add8eca972ab94eb6fe77732b430933188.png","timeStamp":1620634661749},{"screenshot":"aed2bcc4d1f6e367fd4025809f317d9365c1d2f79ed5ef9acc205c595068d768.png","timeStamp":1620634661970}],"result":"SUCCESS","precondition":false,"level":3},{"number":21,"description":"he selects  \u0027Economy\u0027 from Travel Class dropdown","duration":1183,"startTime":"2021-05-10T08:17:41.971333700Z[Etc/UTC]","screenshots":[{"screenshot":"aed2bcc4d1f6e367fd4025809f317d9365c1d2f79ed5ef9acc205c595068d768.png","timeStamp":1620634661973},{"screenshot":"a096e3e0758e5d80af7dd959c1be4e4ae214f50b505803bc2a86439d93a725bf.png","timeStamp":1620634663154}],"result":"SUCCESS","precondition":false,"level":3,"children":[{"number":22,"description":"he clicks on Travel Class dropdown","duration":438,"startTime":"2021-05-10T08:17:41.974331418Z[Etc/UTC]","screenshots":[{"screenshot":"aed2bcc4d1f6e367fd4025809f317d9365c1d2f79ed5ef9acc205c595068d768.png","timeStamp":1620634661978},{"screenshot":"5e911c68965311d199c53271ca5a202d8d629b979e367cdaf15e8a769a8db4be.png","timeStamp":1620634662412}],"result":"SUCCESS","precondition":false,"level":4},{"number":23,"description":"he clicks on option","duration":595,"startTime":"2021-05-10T08:17:42.555976645Z[Etc/UTC]","screenshots":[{"screenshot":"cc1f4f8eec3dd6795ad2bdabf908a5833b2e8381ef3838df176742ee873629bc.png","timeStamp":1620634662732},{"screenshot":"a096e3e0758e5d80af7dd959c1be4e4ae214f50b505803bc2a86439d93a725bf.png","timeStamp":1620634663151}],"result":"SUCCESS","precondition":false,"level":4}]},{"number":24,"description":"he clicks on Search button","duration":463,"startTime":"2021-05-10T08:17:43.155439077Z[Etc/UTC]","screenshots":[{"screenshot":"a096e3e0758e5d80af7dd959c1be4e4ae214f50b505803bc2a86439d93a725bf.png","timeStamp":1620634663157},{"screenshot":"86b8b16820ffa3ecd408d891dc0b84b728a9ad5c3c4813c78fe5f3d6ac2b6243.png","timeStamp":1620634663619}],"result":"SUCCESS","precondition":false,"level":3}]},{"number":25,"description":"he books the first available flight","duration":427,"startTime":"2021-05-10T08:17:46.845157350Z[Etc/UTC]","screenshots":[{"screenshot":"c649aeeb61e4343443f4388d4aad62a04cda4b2095d314b4c520a6278cadcda1.png","timeStamp":1620634666846},{"screenshot":"562f0b1e4721f2f95ca9812985a67d4a842940d2c56ae28f07c31ebe6f49ab9a.png","timeStamp":1620634667272}],"result":"SUCCESS","precondition":false,"level":2,"children":[{"number":26,"description":"he clicks on From field","duration":422,"startTime":"2021-05-10T08:17:46.847508064Z[Etc/UTC]","screenshots":[{"screenshot":"c649aeeb61e4343443f4388d4aad62a04cda4b2095d314b4c520a6278cadcda1.png","timeStamp":1620634666849},{"screenshot":"562f0b1e4721f2f95ca9812985a67d4a842940d2c56ae28f07c31ebe6f49ab9a.png","timeStamp":1620634667269}],"result":"SUCCESS","precondition":false,"level":3}]},{"number":27,"description":"he acknowledges the success notification message","duration":2783,"startTime":"2021-05-10T08:17:47.274789940Z[Etc/UTC]","screenshots":[{"screenshot":"562f0b1e4721f2f95ca9812985a67d4a842940d2c56ae28f07c31ebe6f49ab9a.png","timeStamp":1620634667276},{"screenshot":"441bc43a482312e1592cd31058b9b9b70421ad2a697a07aee0613087ff8ebc05.png","timeStamp":1620634670058}],"result":"SUCCESS","precondition":false,"level":2,"children":[{"number":28,"description":"he clicks on Success message","duration":578,"startTime":"2021-05-10T08:17:47.338048506Z[Etc/UTC]","screenshots":[{"screenshot":"0952a201e3bba1ff6322c83b4884840a81716ae2aaf976dcc0ff0c8ca0eb54e9.png","timeStamp":1620634667495},{"screenshot":"abb16350b1167a472a31e1f75be9a65fdb9bfc9142a2f04c0badc5c31bc3d774.png","timeStamp":1620634667916}],"result":"SUCCESS","precondition":false,"level":3}]}]},{"number":29,"description":"Then he should earn 100 points","duration":780,"startTime":"2021-05-10T08:17:50.061000287Z[Etc/UTC]","screenshots":[{"screenshot":"441bc43a482312e1592cd31058b9b9b70421ad2a697a07aee0613087ff8ebc05.png","timeStamp":1620634670062},{"screenshot":"f48482bf6147f6b1bdcde8e05ba6e66d92a0043bbed9c2fec3f4813a67c769da.png","timeStamp":1620634670841}],"result":"SUCCESS","precondition":false,"level":1,"children":[{"number":30,"description":"he goes to the My Accounts page","duration":744,"startTime":"2021-05-10T08:17:50.064666208Z[Etc/UTC]","screenshots":[{"screenshot":"441bc43a482312e1592cd31058b9b9b70421ad2a697a07aee0613087ff8ebc05.png","timeStamp":1620634670066},{"screenshot":"f48482bf6147f6b1bdcde8e05ba6e66d92a0043bbed9c2fec3f4813a67c769da.png","timeStamp":1620634670809}],"result":"SUCCESS","precondition":false,"level":2,"children":[{"number":31,"description":"he clicks on My Account button","duration":443,"startTime":"2021-05-10T08:17:50.066782520Z[Etc/UTC]","screenshots":[{"screenshot":"441bc43a482312e1592cd31058b9b9b70421ad2a697a07aee0613087ff8ebc05.png","timeStamp":1620634670069},{"screenshot":"28336333d1e687c84a671d3eed08e370af3a05c6f9ac85c9b4bcb71397638733.png","timeStamp":1620634670510}],"result":"SUCCESS","precondition":false,"level":3}]}]}]},{"number":32,"description":"2: Travellers with BRONZE level should earn 25% bonus points ({Status\u003dBRONZE, Points Earned\u003d125, Bonus\u003d25%})","duration":15153,"startTime":"2021-05-10T08:17:51.474729180Z[Etc/UTC]","screenshots":[{"screenshot":"a46b244f53731090f819d9fdcf09f3c2daa260bef93c9893ea34453f42ce2932.png","timeStamp":1620634686628}],"result":"SUCCESS","precondition":false,"level":0,"lineNumber":94,"children":[{"number":33,"description":"Given Trevor is a Frequent Flyer Member with status BRONZE","duration":232,"startTime":"2021-05-10T08:17:51.475833586Z[Etc/UTC]","result":"SUCCESS","precondition":false,"level":1},{"number":34,"description":"And he has logged onto the Frequent Flyer application","duration":4785,"startTime":"2021-05-10T08:17:51.708597435Z[Etc/UTC]","screenshots":[{"screenshot":"c9d26a99f16be46749b5bd010577f928b331f52a0539c35bfacc0bb63097238c.png","timeStamp":1620634676494}],"result":"SUCCESS","precondition":false,"level":1,"children":[{"number":35,"description":"he logs in as trevor-715210562@traveller.com","duration":4167,"startTime":"2021-05-10T08:17:51.711635753Z[Etc/UTC]","screenshots":[{"screenshot":"964133e0bdce079ed92fbaea5cdbf83371ddeea415e9f17d13955303bb37c01f.png","timeStamp":1620634675879}],"result":"SUCCESS","precondition":false,"level":2,"children":[{"number":36,"description":"he goes to the login page","duration":3589,"startTime":"2021-05-10T08:17:51.712156956Z[Etc/UTC]","screenshots":[{"screenshot":"9281d7a44180d9532aad172a87f206187cd891bb2b2dd7babc7b65dcd60cf529.png","timeStamp":1620634675301}],"result":"SUCCESS","precondition":false,"level":3,"children":[{"number":37,"description":"he opens the pages.home page","duration":3148,"startTime":"2021-05-10T08:17:51.713071761Z[Etc/UTC]","screenshots":[{"screenshot":"5e6c6fe116f7dbc6222e6991efb3ce925f993a23cc6cc0738806158c1bdaad47.png","timeStamp":1620634674861}],"result":"SUCCESS","precondition":false,"level":4},{"number":38,"description":"he clicks on Login button","duration":436,"startTime":"2021-05-10T08:17:54.862367018Z[Etc/UTC]","screenshots":[{"screenshot":"5e6c6fe116f7dbc6222e6991efb3ce925f993a23cc6cc0738806158c1bdaad47.png","timeStamp":1620634674866},{"screenshot":"9281d7a44180d9532aad172a87f206187cd891bb2b2dd7babc7b65dcd60cf529.png","timeStamp":1620634675299}],"result":"SUCCESS","precondition":false,"level":4}]},{"number":39,"description":"he enters \u0027trevor-715210562@traveller.com\u0027 into Email field","duration":169,"startTime":"2021-05-10T08:17:55.302182267Z[Etc/UTC]","screenshots":[{"screenshot":"9281d7a44180d9532aad172a87f206187cd891bb2b2dd7babc7b65dcd60cf529.png","timeStamp":1620634675304},{"screenshot":"f4091ea6ae0a6344578dcf85e2fa2aeec87352ac84cbe726bbc5d379a1e5ae66.png","timeStamp":1620634675472}],"result":"SUCCESS","precondition":false,"level":3},{"number":40,"description":"he enters \u0027tr3vor\u0027 into Password field","duration":28,"startTime":"2021-05-10T08:17:55.472837957Z[Etc/UTC]","screenshots":[{"screenshot":"f4091ea6ae0a6344578dcf85e2fa2aeec87352ac84cbe726bbc5d379a1e5ae66.png","timeStamp":1620634675476},{"screenshot":"f4091ea6ae0a6344578dcf85e2fa2aeec87352ac84cbe726bbc5d379a1e5ae66.png","timeStamp":1620634675501}],"result":"SUCCESS","precondition":false,"level":3},{"number":41,"description":"he clicks on Login button","duration":375,"startTime":"2021-05-10T08:17:55.501664024Z[Etc/UTC]","screenshots":[{"screenshot":"f4091ea6ae0a6344578dcf85e2fa2aeec87352ac84cbe726bbc5d379a1e5ae66.png","timeStamp":1620634675504},{"screenshot":"964133e0bdce079ed92fbaea5cdbf83371ddeea415e9f17d13955303bb37c01f.png","timeStamp":1620634675877}],"result":"SUCCESS","precondition":false,"level":3}]},{"number":42,"description":"he expects to see a message of \u0027Logged in as trevor-715210562@traveller.com\u0027","duration":612,"startTime":"2021-05-10T08:17:55.879902216Z[Etc/UTC]","screenshots":[{"screenshot":"964133e0bdce079ed92fbaea5cdbf83371ddeea415e9f17d13955303bb37c01f.png","timeStamp":1620634675881},{"screenshot":"c9d26a99f16be46749b5bd010577f928b331f52a0539c35bfacc0bb63097238c.png","timeStamp":1620634676492}],"result":"SUCCESS","precondition":false,"level":2,"children":[{"number":43,"description":"he should see Success message with text content that is equal to: \u003c\"Logged in as trevor-715210562@traveller.com\"\u003e","duration":159,"startTime":"2021-05-10T08:17:55.957068464Z[Etc/UTC]","screenshots":[{"screenshot":"ed598bfc4cf87339e629d6154700b0a45d68d2ab80555fb4794748e0cf64849a.png","timeStamp":1620634676088},{"screenshot":"ed598bfc4cf87339e629d6154700b0a45d68d2ab80555fb4794748e0cf64849a.png","timeStamp":1620634676116}],"result":"SUCCESS","precondition":false,"level":3},{"number":44,"description":"he clicks on Success message","duration":372,"startTime":"2021-05-10T08:17:56.117134192Z[Etc/UTC]","screenshots":[{"screenshot":"ed598bfc4cf87339e629d6154700b0a45d68d2ab80555fb4794748e0cf64849a.png","timeStamp":1620634676120},{"screenshot":"c9d26a99f16be46749b5bd010577f928b331f52a0539c35bfacc0bb63097238c.png","timeStamp":1620634676490}],"result":"SUCCESS","precondition":false,"level":3}]}]},{"number":45,"description":"When he books an Economy flight from Sydney to Hong Kong","duration":9363,"startTime":"2021-05-10T08:17:56.494731681Z[Etc/UTC]","screenshots":[{"screenshot":"c9d26a99f16be46749b5bd010577f928b331f52a0539c35bfacc0bb63097238c.png","timeStamp":1620634676495},{"screenshot":"27e717815222d3eda2dd64182258ce8d89ffb6477992a135e0f637742e3ff8dc.png","timeStamp":1620634685858}],"result":"SUCCESS","precondition":false,"level":1,"children":[{"number":46,"description":"He search flights","duration":6136,"startTime":"2021-05-10T08:17:56.498170801Z[Etc/UTC]","screenshots":[{"screenshot":"c9d26a99f16be46749b5bd010577f928b331f52a0539c35bfacc0bb63097238c.png","timeStamp":1620634676499},{"screenshot":"72479517dd84006b44cb07f57795bb5aafc8fe788db267620009ef7c62ec6184.png","timeStamp":1620634682634}],"result":"SUCCESS","precondition":false,"level":2,"children":[{"number":47,"description":"he goes to the Book FLights page","duration":1036,"startTime":"2021-05-10T08:17:56.503293030Z[Etc/UTC]","screenshots":[{"screenshot":"c9d26a99f16be46749b5bd010577f928b331f52a0539c35bfacc0bb63097238c.png","timeStamp":1620634676505},{"screenshot":"69000e0ff4e337e888af94df734dac5841a14b5e6ef0dd469181f901dc3f3535.png","timeStamp":1620634677540}],"result":"SUCCESS","precondition":false,"level":3,"children":[{"number":48,"description":"he opens the pages.home page","duration":500,"startTime":"2021-05-10T08:17:56.506798151Z[Etc/UTC]","screenshots":[{"screenshot":"c9d26a99f16be46749b5bd010577f928b331f52a0539c35bfacc0bb63097238c.png","timeStamp":1620634676510},{"screenshot":"af2de890cc8bbb4db11bb6e3b26552b253833e5a9a1639e65b3682c40dbbfc28.png","timeStamp":1620634677007}],"result":"SUCCESS","precondition":false,"level":4},{"number":49,"description":"he clicks on Book Flights button","duration":528,"startTime":"2021-05-10T08:17:57.008277558Z[Etc/UTC]","screenshots":[{"screenshot":"af2de890cc8bbb4db11bb6e3b26552b253833e5a9a1639e65b3682c40dbbfc28.png","timeStamp":1620634677012},{"screenshot":"69000e0ff4e337e888af94df734dac5841a14b5e6ef0dd469181f901dc3f3535.png","timeStamp":1620634677536}],"result":"SUCCESS","precondition":false,"level":4}]},{"number":50,"description":"he enters \u0027Sydney\u0027,TAB into From field","duration":196,"startTime":"2021-05-10T08:17:57.540957246Z[Etc/UTC]","screenshots":[{"screenshot":"69000e0ff4e337e888af94df734dac5841a14b5e6ef0dd469181f901dc3f3535.png","timeStamp":1620634677543},{"screenshot":"0f89109f16f3080fcc445f1ec674b074bfd23b946326c07d2ec17846c9b9339c.png","timeStamp":1620634677737}],"result":"SUCCESS","precondition":false,"level":3},{"number":51,"description":"he enters \u0027Hong Kong\u0027,TAB into To field","duration":208,"startTime":"2021-05-10T08:17:57.737787587Z[Etc/UTC]","screenshots":[{"screenshot":"0f89109f16f3080fcc445f1ec674b074bfd23b946326c07d2ec17846c9b9339c.png","timeStamp":1620634677740},{"screenshot":"b8f74ab9e0f3c57057e63859f71451249f5223acc7a139dfedf2709209f8eab4.png","timeStamp":1620634677946}],"result":"SUCCESS","precondition":false,"level":3},{"number":52,"description":"he selects  \u0027Economy\u0027 from Travel Class dropdown","duration":1127,"startTime":"2021-05-10T08:17:57.947496803Z[Etc/UTC]","screenshots":[{"screenshot":"b8f74ab9e0f3c57057e63859f71451249f5223acc7a139dfedf2709209f8eab4.png","timeStamp":1620634677949},{"screenshot":"641ad8dc19ce5c950104252cd9f6171d809a816a6a1e4fdc387de5f611aabb74.png","timeStamp":1620634679074}],"result":"SUCCESS","precondition":false,"level":3,"children":[{"number":53,"description":"he clicks on Travel Class dropdown","duration":446,"startTime":"2021-05-10T08:17:57.950466720Z[Etc/UTC]","screenshots":[{"screenshot":"b8f74ab9e0f3c57057e63859f71451249f5223acc7a139dfedf2709209f8eab4.png","timeStamp":1620634677953},{"screenshot":"0ae87bf087517670abbbc0e5d467ef31e8b7d40bd9ca280f9d87cfe0e8c1360b.png","timeStamp":1620634678396}],"result":"SUCCESS","precondition":false,"level":4},{"number":54,"description":"he clicks on option","duration":605,"startTime":"2021-05-10T08:17:58.465498606Z[Etc/UTC]","screenshots":[{"screenshot":"4245edc38bbf5e11ce6c074500d0761c1649e95d79d2ec39e9959c6ca0ffcf01.png","timeStamp":1620634678640},{"screenshot":"641ad8dc19ce5c950104252cd9f6171d809a816a6a1e4fdc387de5f611aabb74.png","timeStamp":1620634679071}],"result":"SUCCESS","precondition":false,"level":4}]},{"number":55,"description":"he clicks on Search button","duration":424,"startTime":"2021-05-10T08:17:59.075375241Z[Etc/UTC]","screenshots":[{"screenshot":"641ad8dc19ce5c950104252cd9f6171d809a816a6a1e4fdc387de5f611aabb74.png","timeStamp":1620634679078},{"screenshot":"88426e4c22ccac3c644daf901d758da1a1e4a2ebe4d178a7b1d5886e72dc1ab7.png","timeStamp":1620634679500}],"result":"SUCCESS","precondition":false,"level":3}]},{"number":56,"description":"he books the first available flight","duration":439,"startTime":"2021-05-10T08:18:02.635756758Z[Etc/UTC]","screenshots":[{"screenshot":"72479517dd84006b44cb07f57795bb5aafc8fe788db267620009ef7c62ec6184.png","timeStamp":1620634682637},{"screenshot":"11af196e67051a34efd48fb3425666a87ff95d4f9500b601467130d5f9f41549.png","timeStamp":1620634683075}],"result":"SUCCESS","precondition":false,"level":2,"children":[{"number":57,"description":"he clicks on From field","duration":435,"startTime":"2021-05-10T08:18:02.637821670Z[Etc/UTC]","screenshots":[{"screenshot":"72479517dd84006b44cb07f57795bb5aafc8fe788db267620009ef7c62ec6184.png","timeStamp":1620634682640},{"screenshot":"11af196e67051a34efd48fb3425666a87ff95d4f9500b601467130d5f9f41549.png","timeStamp":1620634683073}],"result":"SUCCESS","precondition":false,"level":3}]},{"number":58,"description":"he acknowledges the success notification message","duration":2777,"startTime":"2021-05-10T08:18:03.078820223Z[Etc/UTC]","screenshots":[{"screenshot":"11af196e67051a34efd48fb3425666a87ff95d4f9500b601467130d5f9f41549.png","timeStamp":1620634683080},{"screenshot":"27e717815222d3eda2dd64182258ce8d89ffb6477992a135e0f637742e3ff8dc.png","timeStamp":1620634685856}],"result":"SUCCESS","precondition":false,"level":2,"children":[{"number":59,"description":"he clicks on Success message","duration":585,"startTime":"2021-05-10T08:18:03.142873393Z[Etc/UTC]","screenshots":[{"screenshot":"900fefd16a20249f13b3cd3a89c6142b1f0ae6f32b42ad373b6ff8d89694c587.png","timeStamp":1620634683312},{"screenshot":"6af808c000e2a58de6ac403d44e0bbc6199a05c7c836276f220422088b06c097.png","timeStamp":1620634683728}],"result":"SUCCESS","precondition":false,"level":3}]}]},{"number":60,"description":"Then he should earn 125 points","duration":767,"startTime":"2021-05-10T08:18:05.859490317Z[Etc/UTC]","screenshots":[{"screenshot":"27e717815222d3eda2dd64182258ce8d89ffb6477992a135e0f637742e3ff8dc.png","timeStamp":1620634685860},{"screenshot":"a46b244f53731090f819d9fdcf09f3c2daa260bef93c9893ea34453f42ce2932.png","timeStamp":1620634686627}],"result":"SUCCESS","precondition":false,"level":1,"children":[{"number":61,"description":"he goes to the My Accounts page","duration":728,"startTime":"2021-05-10T08:18:05.862926837Z[Etc/UTC]","screenshots":[{"screenshot":"27e717815222d3eda2dd64182258ce8d89ffb6477992a135e0f637742e3ff8dc.png","timeStamp":1620634685864},{"screenshot":"a46b244f53731090f819d9fdcf09f3c2daa260bef93c9893ea34453f42ce2932.png","timeStamp":1620634686591}],"result":"SUCCESS","precondition":false,"level":2,"children":[{"number":62,"description":"he clicks on My Account button","duration":421,"startTime":"2021-05-10T08:18:05.865063250Z[Etc/UTC]","screenshots":[{"screenshot":"27e717815222d3eda2dd64182258ce8d89ffb6477992a135e0f637742e3ff8dc.png","timeStamp":1620634685867},{"screenshot":"37ac86c3c34d948e6cc297d9cd49a6c7a3e675212e6e799f118fb126b4f6a505.png","timeStamp":1620634686286}],"result":"SUCCESS","precondition":false,"level":3}]}]}]},{"number":63,"description":"3: Travellers with SILVER level should earn 50% bonus points ({Status\u003dSILVER, Points Earned\u003d150, Bonus\u003d50%})","duration":15215,"startTime":"2021-05-10T08:18:07.188885412Z[Etc/UTC]","screenshots":[{"screenshot":"79e63992d44ce42b0d4aadcdd77a3a54b4a204bf0ca1d29313941d508c4f90ae.png","timeStamp":1620634702404}],"result":"SUCCESS","precondition":false,"level":0,"lineNumber":95,"children":[{"number":64,"description":"Given Trevor is a Frequent Flyer Member with status SILVER","duration":212,"startTime":"2021-05-10T08:18:07.190144419Z[Etc/UTC]","result":"SUCCESS","precondition":false,"level":1},{"number":65,"description":"And he has logged onto the Frequent Flyer application","duration":4471,"startTime":"2021-05-10T08:18:07.402794350Z[Etc/UTC]","screenshots":[{"screenshot":"9dd8887081010dec2641423e1bb6a155f3fe9616477d12f66ecc631bdc0a6992.png","timeStamp":1620634691873}],"result":"SUCCESS","precondition":false,"level":1,"children":[{"number":66,"description":"he logs in as trevor-1697175784@traveller.com","duration":3875,"startTime":"2021-05-10T08:18:07.405188864Z[Etc/UTC]","screenshots":[{"screenshot":"c26ecff7e11b11cd1be8ba7acddd9becf8f952e927b5dc5b52ccbcc75f8434a1.png","timeStamp":1620634691281}],"result":"SUCCESS","precondition":false,"level":2,"children":[{"number":67,"description":"he goes to the login page","duration":3218,"startTime":"2021-05-10T08:18:07.405705267Z[Etc/UTC]","screenshots":[{"screenshot":"eb8fcfec5b784ca69b821036198736fdcf45829c47c7a0945ac8f99962513149.png","timeStamp":1620634690624}],"result":"SUCCESS","precondition":false,"level":3,"children":[{"number":68,"description":"he opens the pages.home page","duration":2762,"startTime":"2021-05-10T08:18:07.406318371Z[Etc/UTC]","screenshots":[{"screenshot":"5e6c6fe116f7dbc6222e6991efb3ce925f993a23cc6cc0738806158c1bdaad47.png","timeStamp":1620634690168}],"result":"SUCCESS","precondition":false,"level":4},{"number":69,"description":"he clicks on Login button","duration":451,"startTime":"2021-05-10T08:18:10.169574438Z[Etc/UTC]","screenshots":[{"screenshot":"5e6c6fe116f7dbc6222e6991efb3ce925f993a23cc6cc0738806158c1bdaad47.png","timeStamp":1620634690173},{"screenshot":"eb8fcfec5b784ca69b821036198736fdcf45829c47c7a0945ac8f99962513149.png","timeStamp":1620634690621}],"result":"SUCCESS","precondition":false,"level":4}]},{"number":70,"description":"he enters \u0027trevor-1697175784@traveller.com\u0027 into Email field","duration":204,"startTime":"2021-05-10T08:18:10.625001891Z[Etc/UTC]","screenshots":[{"screenshot":"eb8fcfec5b784ca69b821036198736fdcf45829c47c7a0945ac8f99962513149.png","timeStamp":1620634690627},{"screenshot":"78e4ea474ba898258e24e14d6c24c2ec258f3cf1441441476e850179bb6fb409.png","timeStamp":1620634690829}],"result":"SUCCESS","precondition":false,"level":3},{"number":71,"description":"he enters \u0027tr3vor\u0027 into Password field","duration":27,"startTime":"2021-05-10T08:18:10.830747289Z[Etc/UTC]","screenshots":[{"screenshot":"78e4ea474ba898258e24e14d6c24c2ec258f3cf1441441476e850179bb6fb409.png","timeStamp":1620634690833},{"screenshot":"78e4ea474ba898258e24e14d6c24c2ec258f3cf1441441476e850179bb6fb409.png","timeStamp":1620634690858}],"result":"SUCCESS","precondition":false,"level":3},{"number":72,"description":"he clicks on Login button","duration":416,"startTime":"2021-05-10T08:18:10.862830176Z[Etc/UTC]","screenshots":[{"screenshot":"78e4ea474ba898258e24e14d6c24c2ec258f3cf1441441476e850179bb6fb409.png","timeStamp":1620634690865},{"screenshot":"c26ecff7e11b11cd1be8ba7acddd9becf8f952e927b5dc5b52ccbcc75f8434a1.png","timeStamp":1620634691279}],"result":"SUCCESS","precondition":false,"level":3}]},{"number":73,"description":"he expects to see a message of \u0027Logged in as trevor-1697175784@traveller.com\u0027","duration":590,"startTime":"2021-05-10T08:18:11.281834016Z[Etc/UTC]","screenshots":[{"screenshot":"c26ecff7e11b11cd1be8ba7acddd9becf8f952e927b5dc5b52ccbcc75f8434a1.png","timeStamp":1620634691283},{"screenshot":"9dd8887081010dec2641423e1bb6a155f3fe9616477d12f66ecc631bdc0a6992.png","timeStamp":1620634691872}],"result":"SUCCESS","precondition":false,"level":2,"children":[{"number":74,"description":"he should see Success message with text content that is equal to: \u003c\"Logged in as trevor-1697175784@traveller.com\"\u003e","duration":142,"startTime":"2021-05-10T08:18:11.346420192Z[Etc/UTC]","screenshots":[{"screenshot":"e9c924c9b591dd594d4694dc17aa56acd692d6d08a8dee1e49d41a99a5cc9ee3.png","timeStamp":1620634691462},{"screenshot":"e9c924c9b591dd594d4694dc17aa56acd692d6d08a8dee1e49d41a99a5cc9ee3.png","timeStamp":1620634691489}],"result":"SUCCESS","precondition":false,"level":3},{"number":75,"description":"he clicks on Success message","duration":379,"startTime":"2021-05-10T08:18:11.490549832Z[Etc/UTC]","screenshots":[{"screenshot":"e9c924c9b591dd594d4694dc17aa56acd692d6d08a8dee1e49d41a99a5cc9ee3.png","timeStamp":1620634691493},{"screenshot":"9dd8887081010dec2641423e1bb6a155f3fe9616477d12f66ecc631bdc0a6992.png","timeStamp":1620634691870}],"result":"SUCCESS","precondition":false,"level":3}]}]},{"number":76,"description":"When he books an Economy flight from Sydney to Hong Kong","duration":9749,"startTime":"2021-05-10T08:18:11.874451467Z[Etc/UTC]","screenshots":[{"screenshot":"9dd8887081010dec2641423e1bb6a155f3fe9616477d12f66ecc631bdc0a6992.png","timeStamp":1620634691875},{"screenshot":"ac59a8de91fe1a5777f58f87ba6e16ea0758aa8a4a14457774063df924d5a5b2.png","timeStamp":1620634701623}],"result":"SUCCESS","precondition":false,"level":1,"children":[{"number":77,"description":"He search flights","duration":6524,"startTime":"2021-05-10T08:18:11.878295990Z[Etc/UTC]","screenshots":[{"screenshot":"9dd8887081010dec2641423e1bb6a155f3fe9616477d12f66ecc631bdc0a6992.png","timeStamp":1620634691880},{"screenshot":"a4dd4d9472e53da3d46a86871ffd740339fb63ed21c7c7e8d0c91ebb977a0db1.png","timeStamp":1620634698403}],"result":"SUCCESS","precondition":false,"level":2,"children":[{"number":78,"description":"he goes to the Book FLights page","duration":1004,"startTime":"2021-05-10T08:18:11.883221419Z[Etc/UTC]","screenshots":[{"screenshot":"9dd8887081010dec2641423e1bb6a155f3fe9616477d12f66ecc631bdc0a6992.png","timeStamp":1620634691885},{"screenshot":"55c602820e6ec4560946a44c087a0187508b81c47e8ce6864f02a3ea5af6d9d9.png","timeStamp":1620634692887}],"result":"SUCCESS","precondition":false,"level":3,"children":[{"number":79,"description":"he opens the pages.home page","duration":453,"startTime":"2021-05-10T08:18:11.886379537Z[Etc/UTC]","screenshots":[{"screenshot":"9dd8887081010dec2641423e1bb6a155f3fe9616477d12f66ecc631bdc0a6992.png","timeStamp":1620634691891},{"screenshot":"75cd6300547aee9450b4dee6bc575db558c5a0633e172c43f7a3e41984f642fb.png","timeStamp":1620634692339}],"result":"SUCCESS","precondition":false,"level":4},{"number":80,"description":"he clicks on Book Flights button","duration":544,"startTime":"2021-05-10T08:18:12.340581182Z[Etc/UTC]","screenshots":[{"screenshot":"75cd6300547aee9450b4dee6bc575db558c5a0633e172c43f7a3e41984f642fb.png","timeStamp":1620634692345},{"screenshot":"55c602820e6ec4560946a44c087a0187508b81c47e8ce6864f02a3ea5af6d9d9.png","timeStamp":1620634692885}],"result":"SUCCESS","precondition":false,"level":4}]},{"number":81,"description":"he enters \u0027Sydney\u0027,TAB into From field","duration":234,"startTime":"2021-05-10T08:18:12.888190071Z[Etc/UTC]","screenshots":[{"screenshot":"55c602820e6ec4560946a44c087a0187508b81c47e8ce6864f02a3ea5af6d9d9.png","timeStamp":1620634692891},{"screenshot":"94200c2d27261e3c2b39d9ccfeaf92ba53b1ad0a55336d8d11b4fd705205c5c5.png","timeStamp":1620634693122}],"result":"SUCCESS","precondition":false,"level":3},{"number":82,"description":"he enters \u0027Hong Kong\u0027,TAB into To field","duration":207,"startTime":"2021-05-10T08:18:13.123333541Z[Etc/UTC]","screenshots":[{"screenshot":"94200c2d27261e3c2b39d9ccfeaf92ba53b1ad0a55336d8d11b4fd705205c5c5.png","timeStamp":1620634693125},{"screenshot":"f7caf85e18d2a95cf74c5e0a6b5acba972f24f5aa932ed33ed796187c7042c85.png","timeStamp":1620634693330}],"result":"SUCCESS","precondition":false,"level":3},{"number":83,"description":"he selects  \u0027Economy\u0027 from Travel Class dropdown","duration":1121,"startTime":"2021-05-10T08:18:13.331784955Z[Etc/UTC]","screenshots":[{"screenshot":"f7caf85e18d2a95cf74c5e0a6b5acba972f24f5aa932ed33ed796187c7042c85.png","timeStamp":1620634693334},{"screenshot":"45bb57df31121773152deafacd94316302e384187e2c761b7f3ccca5e76c75b3.png","timeStamp":1620634694452}],"result":"SUCCESS","precondition":false,"level":3,"children":[{"number":84,"description":"he clicks on Travel Class dropdown","duration":463,"startTime":"2021-05-10T08:18:13.334811973Z[Etc/UTC]","screenshots":[{"screenshot":"f7caf85e18d2a95cf74c5e0a6b5acba972f24f5aa932ed33ed796187c7042c85.png","timeStamp":1620634693338},{"screenshot":"e4756991c91e63136e1bac528d5c4e19696c5908d0ee7da1668f8722825c56a6.png","timeStamp":1620634693798}],"result":"SUCCESS","precondition":false,"level":4},{"number":85,"description":"he clicks on option","duration":579,"startTime":"2021-05-10T08:18:13.870718794Z[Etc/UTC]","screenshots":[{"screenshot":"35e66155a8664b6da7f916f3d7fc1ce361dfdb06490cab687caae26e298f8250.png","timeStamp":1620634694027},{"screenshot":"45bb57df31121773152deafacd94316302e384187e2c761b7f3ccca5e76c75b3.png","timeStamp":1620634694450}],"result":"SUCCESS","precondition":false,"level":4}]},{"number":86,"description":"he clicks on Search button","duration":406,"startTime":"2021-05-10T08:18:14.453655189Z[Etc/UTC]","screenshots":[{"screenshot":"45bb57df31121773152deafacd94316302e384187e2c761b7f3ccca5e76c75b3.png","timeStamp":1620634694456},{"screenshot":"6c55f44d66981e9c0bae8a73326996c4ba739ebe9df21e5c30b8941f75f28d5e.png","timeStamp":1620634694860}],"result":"SUCCESS","precondition":false,"level":3}]},{"number":87,"description":"he books the first available flight","duration":427,"startTime":"2021-05-10T08:18:18.403830190Z[Etc/UTC]","screenshots":[{"screenshot":"a4dd4d9472e53da3d46a86871ffd740339fb63ed21c7c7e8d0c91ebb977a0db1.png","timeStamp":1620634698405},{"screenshot":"582be373668f66130d2c710f2f424457c5682ded65dba62866d1d6a9f9b717ff.png","timeStamp":1620634698831}],"result":"SUCCESS","precondition":false,"level":2,"children":[{"number":88,"description":"he clicks on From field","duration":423,"startTime":"2021-05-10T08:18:18.405727102Z[Etc/UTC]","screenshots":[{"screenshot":"a4dd4d9472e53da3d46a86871ffd740339fb63ed21c7c7e8d0c91ebb977a0db1.png","timeStamp":1620634698408},{"screenshot":"582be373668f66130d2c710f2f424457c5682ded65dba62866d1d6a9f9b717ff.png","timeStamp":1620634698829}],"result":"SUCCESS","precondition":false,"level":3}]},{"number":89,"description":"he acknowledges the success notification message","duration":2790,"startTime":"2021-05-10T08:18:18.831818469Z[Etc/UTC]","screenshots":[{"screenshot":"582be373668f66130d2c710f2f424457c5682ded65dba62866d1d6a9f9b717ff.png","timeStamp":1620634698833},{"screenshot":"ac59a8de91fe1a5777f58f87ba6e16ea0758aa8a4a14457774063df924d5a5b2.png","timeStamp":1620634701621}],"result":"SUCCESS","precondition":false,"level":2,"children":[{"number":90,"description":"he clicks on Success message","duration":581,"startTime":"2021-05-10T08:18:18.906922240Z[Etc/UTC]","screenshots":[{"screenshot":"b97d36c0f340426a439218401f0ce5882c699e40ebe72f3d40ce38d9cc57ed8c.png","timeStamp":1620634699076},{"screenshot":"23a0309737d20d553c41189c3356e992f329fb6219294cc58a8b3ea8fe566e3c.png","timeStamp":1620634699488}],"result":"SUCCESS","precondition":false,"level":3}]}]},{"number":91,"description":"Then he should earn 150 points","duration":778,"startTime":"2021-05-10T08:18:21.624271053Z[Etc/UTC]","screenshots":[{"screenshot":"ac59a8de91fe1a5777f58f87ba6e16ea0758aa8a4a14457774063df924d5a5b2.png","timeStamp":1620634701625},{"screenshot":"79e63992d44ce42b0d4aadcdd77a3a54b4a204bf0ca1d29313941d508c4f90ae.png","timeStamp":1620634702402}],"result":"SUCCESS","precondition":false,"level":1,"children":[{"number":92,"description":"he goes to the My Accounts page","duration":743,"startTime":"2021-05-10T08:18:21.627203571Z[Etc/UTC]","screenshots":[{"screenshot":"ac59a8de91fe1a5777f58f87ba6e16ea0758aa8a4a14457774063df924d5a5b2.png","timeStamp":1620634701628},{"screenshot":"79e63992d44ce42b0d4aadcdd77a3a54b4a204bf0ca1d29313941d508c4f90ae.png","timeStamp":1620634702370}],"result":"SUCCESS","precondition":false,"level":2,"children":[{"number":93,"description":"he clicks on My Account button","duration":424,"startTime":"2021-05-10T08:18:21.629101083Z[Etc/UTC]","screenshots":[{"screenshot":"ac59a8de91fe1a5777f58f87ba6e16ea0758aa8a4a14457774063df924d5a5b2.png","timeStamp":1620634701631},{"screenshot":"f7dee7ee238f49d30b32a5697108f9263c51866ba005e3857b71f69e29547f7c.png","timeStamp":1620634702053}],"result":"SUCCESS","precondition":false,"level":3}]}]}]},{"number":94,"description":"4: Travellers with GOLD level should earn 100% bonus points ({Status\u003dGOLD, Points Earned\u003d200, Bonus\u003d100%})","duration":14929,"startTime":"2021-05-10T08:18:23.074639833Z[Etc/UTC]","screenshots":[{"screenshot":"9be31e0243e5b5bd619347aa035cb4b9637c25c609c8f0c413b8627264e244c9.png","timeStamp":1620634718004}],"result":"SUCCESS","precondition":false,"level":0,"lineNumber":96,"children":[{"number":95,"description":"Given Trevor is a Frequent Flyer Member with status GOLD","duration":211,"startTime":"2021-05-10T08:18:23.075895641Z[Etc/UTC]","result":"SUCCESS","precondition":false,"level":1},{"number":96,"description":"And he has logged onto the Frequent Flyer application","duration":4514,"startTime":"2021-05-10T08:18:23.287657167Z[Etc/UTC]","screenshots":[{"screenshot":"cd65161f7b12505715cf00b6d2cde7480ba03b3110f1cfe3ef0d80ef0b986eae.png","timeStamp":1620634707802}],"result":"SUCCESS","precondition":false,"level":1,"children":[{"number":97,"description":"he logs in as trevor21679867@traveller.com","duration":3929,"startTime":"2021-05-10T08:18:23.290811287Z[Etc/UTC]","screenshots":[{"screenshot":"615ae5e858dbce42a11f8e48a33cd135af1fd0e432f19300db867dcd2ba70e88.png","timeStamp":1620634707220}],"result":"SUCCESS","precondition":false,"level":2,"children":[{"number":98,"description":"he goes to the login page","duration":3325,"startTime":"2021-05-10T08:18:23.291359490Z[Etc/UTC]","screenshots":[{"screenshot":"a05190f4f356210ecd0ddb7242387e06e607174d75e725e676fb61578f05a9a8.png","timeStamp":1620634706616}],"result":"SUCCESS","precondition":false,"level":3,"children":[{"number":99,"description":"he opens the pages.home page","duration":2870,"startTime":"2021-05-10T08:18:23.292136695Z[Etc/UTC]","screenshots":[{"screenshot":"5e6c6fe116f7dbc6222e6991efb3ce925f993a23cc6cc0738806158c1bdaad47.png","timeStamp":1620634706162}],"result":"SUCCESS","precondition":false,"level":4},{"number":100,"description":"he clicks on Login button","duration":449,"startTime":"2021-05-10T08:18:26.163529070Z[Etc/UTC]","screenshots":[{"screenshot":"5e6c6fe116f7dbc6222e6991efb3ce925f993a23cc6cc0738806158c1bdaad47.png","timeStamp":1620634706167},{"screenshot":"a05190f4f356210ecd0ddb7242387e06e607174d75e725e676fb61578f05a9a8.png","timeStamp":1620634706612}],"result":"SUCCESS","precondition":false,"level":4}]},{"number":101,"description":"he enters \u0027trevor21679867@traveller.com\u0027 into Email field","duration":183,"startTime":"2021-05-10T08:18:26.617421732Z[Etc/UTC]","screenshots":[{"screenshot":"a05190f4f356210ecd0ddb7242387e06e607174d75e725e676fb61578f05a9a8.png","timeStamp":1620634706620},{"screenshot":"8deb361813b6722785ed5f42c630812576c420e7c196f2957995a0462fce281b.png","timeStamp":1620634706801}],"result":"SUCCESS","precondition":false,"level":3},{"number":102,"description":"he enters \u0027tr3vor\u0027 into Password field","duration":30,"startTime":"2021-05-10T08:18:26.802447417Z[Etc/UTC]","screenshots":[{"screenshot":"8deb361813b6722785ed5f42c630812576c420e7c196f2957995a0462fce281b.png","timeStamp":1620634706805},{"screenshot":"8deb361813b6722785ed5f42c630812576c420e7c196f2957995a0462fce281b.png","timeStamp":1620634706832}],"result":"SUCCESS","precondition":false,"level":3},{"number":103,"description":"he clicks on Login button","duration":385,"startTime":"2021-05-10T08:18:26.833145897Z[Etc/UTC]","screenshots":[{"screenshot":"8deb361813b6722785ed5f42c630812576c420e7c196f2957995a0462fce281b.png","timeStamp":1620634706836},{"screenshot":"615ae5e858dbce42a11f8e48a33cd135af1fd0e432f19300db867dcd2ba70e88.png","timeStamp":1620634707218}],"result":"SUCCESS","precondition":false,"level":3}]},{"number":104,"description":"he expects to see a message of \u0027Logged in as trevor21679867@traveller.com\u0027","duration":579,"startTime":"2021-05-10T08:18:27.221529075Z[Etc/UTC]","screenshots":[{"screenshot":"615ae5e858dbce42a11f8e48a33cd135af1fd0e432f19300db867dcd2ba70e88.png","timeStamp":1620634707222},{"screenshot":"cd65161f7b12505715cf00b6d2cde7480ba03b3110f1cfe3ef0d80ef0b986eae.png","timeStamp":1620634707800}],"result":"SUCCESS","precondition":false,"level":2,"children":[{"number":105,"description":"he should see Success message with text content that is equal to: \u003c\"Logged in as trevor21679867@traveller.com\"\u003e","duration":143,"startTime":"2021-05-10T08:18:27.283357138Z[Etc/UTC]","screenshots":[{"screenshot":"99289eebb90cedbf621d10c3f7118419fc6d8fdba750f9f26ea3997ce8ca5145.png","timeStamp":1620634707398},{"screenshot":"99289eebb90cedbf621d10c3f7118419fc6d8fdba750f9f26ea3997ce8ca5145.png","timeStamp":1620634707426}],"result":"SUCCESS","precondition":false,"level":3},{"number":106,"description":"he clicks on Success message","duration":371,"startTime":"2021-05-10T08:18:27.427173981Z[Etc/UTC]","screenshots":[{"screenshot":"99289eebb90cedbf621d10c3f7118419fc6d8fdba750f9f26ea3997ce8ca5145.png","timeStamp":1620634707429},{"screenshot":"cd65161f7b12505715cf00b6d2cde7480ba03b3110f1cfe3ef0d80ef0b986eae.png","timeStamp":1620634707798}],"result":"SUCCESS","precondition":false,"level":3}]}]},{"number":107,"description":"When he books an Economy flight from Sydney to Hong Kong","duration":9446,"startTime":"2021-05-10T08:18:27.802655383Z[Etc/UTC]","screenshots":[{"screenshot":"cd65161f7b12505715cf00b6d2cde7480ba03b3110f1cfe3ef0d80ef0b986eae.png","timeStamp":1620634707803},{"screenshot":"012f545dbdfc0ce0a2386cd050695f2324c77d4f6350da29247ccd6448e65ffc.png","timeStamp":1620634717249}],"result":"SUCCESS","precondition":false,"level":1,"children":[{"number":108,"description":"He search flights","duration":6159,"startTime":"2021-05-10T08:18:27.806147404Z[Etc/UTC]","screenshots":[{"screenshot":"cd65161f7b12505715cf00b6d2cde7480ba03b3110f1cfe3ef0d80ef0b986eae.png","timeStamp":1620634707808},{"screenshot":"9bab60b91e0f9cb52f95747621f390b09b80b06f78eae877b4cb4d34475f387c.png","timeStamp":1620634713965}],"result":"SUCCESS","precondition":false,"level":2,"children":[{"number":109,"description":"he goes to the Book FLights page","duration":998,"startTime":"2021-05-10T08:18:27.811166633Z[Etc/UTC]","screenshots":[{"screenshot":"cd65161f7b12505715cf00b6d2cde7480ba03b3110f1cfe3ef0d80ef0b986eae.png","timeStamp":1620634707813},{"screenshot":"b71428fe711744355a6dd3a05fce633d572812b3454883840890358b487f1ebf.png","timeStamp":1620634708810}],"result":"SUCCESS","precondition":false,"level":3,"children":[{"number":110,"description":"he opens the pages.home page","duration":470,"startTime":"2021-05-10T08:18:27.814469852Z[Etc/UTC]","screenshots":[{"screenshot":"cd65161f7b12505715cf00b6d2cde7480ba03b3110f1cfe3ef0d80ef0b986eae.png","timeStamp":1620634707818},{"screenshot":"840db09264d0c7de6284af939a39b11e7d7e385f5ccf7438079cc8fda38e2bf4.png","timeStamp":1620634708285}],"result":"SUCCESS","precondition":false,"level":4},{"number":111,"description":"he clicks on Book Flights button","duration":520,"startTime":"2021-05-10T08:18:28.286593821Z[Etc/UTC]","screenshots":[{"screenshot":"840db09264d0c7de6284af939a39b11e7d7e385f5ccf7438079cc8fda38e2bf4.png","timeStamp":1620634708289},{"screenshot":"b71428fe711744355a6dd3a05fce633d572812b3454883840890358b487f1ebf.png","timeStamp":1620634708807}],"result":"SUCCESS","precondition":false,"level":4}]},{"number":112,"description":"he enters \u0027Sydney\u0027,TAB into From field","duration":231,"startTime":"2021-05-10T08:18:28.810602994Z[Etc/UTC]","screenshots":[{"screenshot":"b71428fe711744355a6dd3a05fce633d572812b3454883840890358b487f1ebf.png","timeStamp":1620634708812},{"screenshot":"5efaf63b9bb44f95e5909ad422a9b6565e3a2cbf2399bee90e4e01032a3293de.png","timeStamp":1620634709042}],"result":"SUCCESS","precondition":false,"level":3},{"number":113,"description":"he enters \u0027Hong Kong\u0027,TAB into To field","duration":182,"startTime":"2021-05-10T08:18:29.042807656Z[Etc/UTC]","screenshots":[{"screenshot":"5efaf63b9bb44f95e5909ad422a9b6565e3a2cbf2399bee90e4e01032a3293de.png","timeStamp":1620634709045},{"screenshot":"d2e6c319d8d8c0993e908103ebb96148eca614b63c90475460a7888e7e2c74d0.png","timeStamp":1620634709225}],"result":"SUCCESS","precondition":false,"level":3},{"number":114,"description":"he selects  \u0027Economy\u0027 from Travel Class dropdown","duration":1172,"startTime":"2021-05-10T08:18:29.226033931Z[Etc/UTC]","screenshots":[{"screenshot":"d2e6c319d8d8c0993e908103ebb96148eca614b63c90475460a7888e7e2c74d0.png","timeStamp":1620634709228},{"screenshot":"7f0b762c95dab270d29f94704dce02433aa9044da045876c3633e6a22da33b57.png","timeStamp":1620634710398}],"result":"SUCCESS","precondition":false,"level":3,"children":[{"number":115,"description":"he clicks on Travel Class dropdown","duration":440,"startTime":"2021-05-10T08:18:29.228755147Z[Etc/UTC]","screenshots":[{"screenshot":"d2e6c319d8d8c0993e908103ebb96148eca614b63c90475460a7888e7e2c74d0.png","timeStamp":1620634709232},{"screenshot":"d07c858d2469a5c99eaf731a4d65ace2780aa03d3b3a8d61304f93697332a406.png","timeStamp":1620634709669}],"result":"SUCCESS","precondition":false,"level":4},{"number":116,"description":"he clicks on option","duration":622,"startTime":"2021-05-10T08:18:29.772934638Z[Etc/UTC]","screenshots":[{"screenshot":"baad8c34742f355a12352cb17630e52ca14ade4255a1bf4560b72cb536a792b2.png","timeStamp":1620634709946},{"screenshot":"7f0b762c95dab270d29f94704dce02433aa9044da045876c3633e6a22da33b57.png","timeStamp":1620634710395}],"result":"SUCCESS","precondition":false,"level":4}]},{"number":117,"description":"he clicks on Search button","duration":430,"startTime":"2021-05-10T08:18:30.399269112Z[Etc/UTC]","screenshots":[{"screenshot":"7f0b762c95dab270d29f94704dce02433aa9044da045876c3633e6a22da33b57.png","timeStamp":1620634710401},{"screenshot":"d5aad76615b4daa4a6d507fc78c22b42c9301877923f324822279488f8726a7e.png","timeStamp":1620634710829}],"result":"SUCCESS","precondition":false,"level":3}]},{"number":118,"description":"he books the first available flight","duration":436,"startTime":"2021-05-10T08:18:33.966823313Z[Etc/UTC]","screenshots":[{"screenshot":"9bab60b91e0f9cb52f95747621f390b09b80b06f78eae877b4cb4d34475f387c.png","timeStamp":1620634713968},{"screenshot":"9c29049bbb115e7c0f30311a4a0f78a41dca833c5a8c4a1927e1471812b9117c.png","timeStamp":1620634714403}],"result":"SUCCESS","precondition":false,"level":2,"children":[{"number":119,"description":"he clicks on From field","duration":432,"startTime":"2021-05-10T08:18:33.969170727Z[Etc/UTC]","screenshots":[{"screenshot":"9bab60b91e0f9cb52f95747621f390b09b80b06f78eae877b4cb4d34475f387c.png","timeStamp":1620634713972},{"screenshot":"9c29049bbb115e7c0f30311a4a0f78a41dca833c5a8c4a1927e1471812b9117c.png","timeStamp":1620634714401}],"result":"SUCCESS","precondition":false,"level":3}]},{"number":120,"description":"he acknowledges the success notification message","duration":2843,"startTime":"2021-05-10T08:18:34.403693018Z[Etc/UTC]","screenshots":[{"screenshot":"9c29049bbb115e7c0f30311a4a0f78a41dca833c5a8c4a1927e1471812b9117c.png","timeStamp":1620634714405},{"screenshot":"012f545dbdfc0ce0a2386cd050695f2324c77d4f6350da29247ccd6448e65ffc.png","timeStamp":1620634717247}],"result":"SUCCESS","precondition":false,"level":2,"children":[{"number":121,"description":"he clicks on Success message","duration":588,"startTime":"2021-05-10T08:18:34.512403666Z[Etc/UTC]","screenshots":[{"screenshot":"b975fa1f426ea2d7cc12a6c78e867348c08b1d79ce94d87be9c4098424f6e848.png","timeStamp":1620634714681},{"screenshot":"5dfcf59a1c0ea3b821660266424e38a00d6600ffe2afc01b5741ce6497585929.png","timeStamp":1620634715101}],"result":"SUCCESS","precondition":false,"level":3}]}]},{"number":122,"description":"Then he should earn 200 points","duration":753,"startTime":"2021-05-10T08:18:37.250011289Z[Etc/UTC]","screenshots":[{"screenshot":"012f545dbdfc0ce0a2386cd050695f2324c77d4f6350da29247ccd6448e65ffc.png","timeStamp":1620634717250},{"screenshot":"9be31e0243e5b5bd619347aa035cb4b9637c25c609c8f0c413b8627264e244c9.png","timeStamp":1620634718003}],"result":"SUCCESS","precondition":false,"level":1,"children":[{"number":123,"description":"he goes to the My Accounts page","duration":714,"startTime":"2021-05-10T08:18:37.252718205Z[Etc/UTC]","screenshots":[{"screenshot":"012f545dbdfc0ce0a2386cd050695f2324c77d4f6350da29247ccd6448e65ffc.png","timeStamp":1620634717254},{"screenshot":"9be31e0243e5b5bd619347aa035cb4b9637c25c609c8f0c413b8627264e244c9.png","timeStamp":1620634717967}],"result":"SUCCESS","precondition":false,"level":2,"children":[{"number":124,"description":"he clicks on My Account button","duration":419,"startTime":"2021-05-10T08:18:37.254681917Z[Etc/UTC]","screenshots":[{"screenshot":"012f545dbdfc0ce0a2386cd050695f2324c77d4f6350da29247ccd6448e65ffc.png","timeStamp":1620634717257},{"screenshot":"33baa423ffd7f1be3a4b576d7cacc7177011bbb80fa729391819584176e0704b.png","timeStamp":1620634717674}],"result":"SUCCESS","precondition":false,"level":3}]}]}]}],"userStory":{"id":"earning-points","storyName":"Earning Points","path":"classpath:features/earning_frequent_flyer_points/earning_points.feature","narrative":"  Frequent Flyers earn status points each time they fly.\n  As they earn more points, their status level increases and they get more benefits.","type":"feature"},"featureTag":{"name":"Earning frequent flyer points/Earning Points","type":"feature","displayName":"Earning frequent flyer points/Earning Points"},"title":"Travellers with \u003cStatus\u003e level should earn \u003cBonus\u003e bonus points","description":"    A flight from Sydney to Hong Kong normally earns 100 points","tags":[{"name":"Earning frequent flyer points/Earning Points","type":"feature","displayName":"Earning Points"},{"name":"firefox","type":"browser","displayName":"firefox"},{"name":"earning-points","type":"tag","displayName":"earning-points"},{"name":"firefox","type":"context","displayName":"firefox"},{"name":"Earning frequent flyer points","type":"capability","displayName":"Earning Frequent Flyer Points"}],"startTime":"2021-05-10T08:17:36.073534550Z[Etc/UTC]","duration":62476,"rule":{"name":"Travellers with higher status earn more points","description":""},"projectKey":"","driver":"firefox:trevor","isManualTestingUpToDate":false,"context":"firefox","dataTable":{"headers":["Status","Points Earned","Bonus"],"rows":[{"values":["STANDARD","100","0"],"lineNumber":93,"result":"SUCCESS"},{"values":["BRONZE","125","25%"],"lineNumber":94,"result":"SUCCESS"},{"values":["SILVER","150","50%"],"lineNumber":95,"result":"SUCCESS"},{"values":["GOLD","200","100%"],"lineNumber":96,"result":"SUCCESS"}],"predefinedRows":true,"scenarioOutline":"Given Trevor is a Frequent Flyer Member with status \u003cStatus\u003e\n\rAnd he has logged onto the Frequent Flyer application\n\rWhen he books an Economy flight from Sydney to Hong Kong\n\rThen he should earn \u003cPoints Earned\u003e points\n\r","dataSetDescriptors":[{"startRow":0,"rowCount":0,"name":"","description":""}]},"manual":false,"testSource":"Cucumber","actors":[{"name":"Trevor","can":["browse the web"]}],"result":"SUCCESS","scenarioOutline":"Given Trevor is a Frequent Flyer Member with status \u003cStatus\u003e\nAnd he has logged onto the Frequent Flyer application\nWhen he books an Economy flight from Sydney to Hong Kong\nThen he should earn \u003cPoints Earned\u003e points"}